dbt/adapters/maxcompute/__init__.py
dbt/adapters/maxcompute/__version__.py
dbt/adapters/maxcompute/column.py
dbt/adapters/maxcompute/connections.py
dbt/adapters/maxcompute/context.py
dbt/adapters/maxcompute/credentials.py
dbt/adapters/maxcompute/impl.py
dbt/adapters/maxcompute/relation.py
dbt/adapters/maxcompute/setting_parser.py
dbt/adapters/maxcompute/utils.py
dbt/adapters/maxcompute/wrapper.py
dbt/adapters/maxcompute/relation_configs/__init__.py
dbt/adapters/maxcompute/relation_configs/_base.py
dbt/adapters/maxcompute/relation_configs/_materialized_view.py
dbt/adapters/maxcompute/relation_configs/_partition.py
dbt/adapters/maxcompute/relation_configs/_policies.py
dbt/include/maxcompute/__init__.py
dbt/include/maxcompute/dbt_project.yml
dbt/include/maxcompute/profile_template.yml
dbt/include/maxcompute/macros/adapters.sql
dbt/include/maxcompute/macros/adapters/apply_grants.sql
dbt/include/maxcompute/macros/adapters/columns.sql
dbt/include/maxcompute/macros/adapters/persist_docs.sql
dbt/include/maxcompute/macros/materializations/clone.sql
dbt/include/maxcompute/macros/materializations/hooks.sql
dbt/include/maxcompute/macros/materializations/raw.sql
dbt/include/maxcompute/macros/materializations/incremental/incremental.sql
dbt/include/maxcompute/macros/materializations/incremental/merge.sql
dbt/include/maxcompute/macros/materializations/incremental/incremental_strategy/insert_overwrite.sql
dbt/include/maxcompute/macros/materializations/incremental/incremental_strategy/microbatch.sql
dbt/include/maxcompute/macros/materializations/seeds/seeds.sql
dbt/include/maxcompute/macros/materializations/snapshots/snapshot.sql
dbt/include/maxcompute/macros/relations/partition.sql
dbt/include/maxcompute/macros/relations/materialized_view/alter.sql
dbt/include/maxcompute/macros/relations/materialized_view/create.sql
dbt/include/maxcompute/macros/relations/materialized_view/drop.sql
dbt/include/maxcompute/macros/relations/materialized_view/refresh.sql
dbt_maxcompute-1.9.0a10.dist-info/LICENSE
dbt_maxcompute-1.9.0a10.dist-info/METADATA
dbt_maxcompute-1.9.0a10.dist-info/WHEEL
dbt_maxcompute-1.9.0a10.dist-info/top_level.txt
dbt_maxcompute-1.9.0a10.dist-info/RECORD
