Metadata-Version: 2.1
Name: dbt-maxcompute
Version: 1.9.0a10
Summary: The MaxCompute adapter plugin for dbt
Home-page: https://github.com/dingxin-tech/dbt-maxcompute
Author: Alibaba Cloud MaxCompute Team
Author-email: zhangdingxin.zdx@alibaba-inc.com
Classifier: Development Status :: 3 - Alpha
Classifier: License :: OSI Approved :: Apache Software License
Classifier: Operating System :: Microsoft :: Windows
Classifier: Operating System :: MacOS :: MacOS X
Classifier: Operating System :: POSIX :: Linux
Classifier: Programming Language :: Python :: 3.9
Classifier: Programming Language :: Python :: 3.10
Classifier: Programming Language :: Python :: 3.11
Classifier: Programming Language :: Python :: 3.12
Requires-Python: >=3.9
License-File: LICENSE
Requires-Dist: dbt-common<2.0,>=1.10
Requires-Dist: dbt-adapters<2.0,>=1.7
Requires-Dist: pyodps>=0.12.0
Requires-Dist: alibabacloud_credentials>=0.3.6
Requires-Dist: pandas>=0.17.0
Requires-Dist: dbt-core>=1.8.0
